{
  "meta": {
    "voice": "zh-CN-YunjianNeural",
    "rate": "+25%",
    "bgm_volume": 0.15,
    "bgm_source": "neon-electric-3.mp3"
  },
  "segments": [
    {
      "scene": "hook",
      "actual_duration": 3.79
    },
    {
      "scene": "topic1",
      "actual_duration": 14.42
    },
    {
      "scene": "topic2",
      "actual_duration": 12.17
    },
    {
      "scene": "topic3",
      "actual_duration": 11.83
    },
    {
      "scene": "topic4",
      "actual_duration": 10.85
    },
    {
      "scene": "topic5",
      "actual_duration": 12.89
    },
    {
      "scene": "cta",
      "actual_duration": 2.06
    }
  ]
}